{
  "enabled": false,
  "url": "",
  "domicile_enabled": false,
  "domicile_zones": ["Rhode-Saint-Genèse", "Uccle", "Linkebeek", "Beersel"],
  "domicile_desc": {
    "fr": "Zoé se déplace à votre domicile dans les zones suivantes :",
    "nl": "Zoé komt aan huis in de volgende zones :",
    "en": "Zoé visits you at home in the following areas :"
  },
  "button_text": {
    "fr": "Réserver un Bilan Précision",
    "nl": "Boek een Precisie-audit",
    "en": "Book a Precision Assessment"
  },
  "badge": {
    "fr": "Disponibilité immédiate",
    "nl": "Directe beschikbaarheid",
    "en": "Immediate availability"
  },
  "titre": {
    "fr": "Réserver un Bilan Précision",
    "nl": "Boek een Precisie-audit",
    "en": "Book a Precision Assessment"
  },
  "description": {
    "fr": "Choisissez directement votre créneau dans l'agenda de Zoé.",
    "nl": "Kies direct uw tijdslot in de agenda van Zoé.",
    "en": "Choose your slot directly in Zoé's calendar."
  },
  "detail": {
    "fr": "30 min · 60€",
    "nl": "30 min · 60€",
    "en": "30 min · 60€"
  },
  "btn": {
    "fr": "Réserver maintenant",
    "nl": "Nu reserveren",
    "en": "Book now"
  },
  "separateur": {
    "fr": "ou",
    "nl": "of",
    "en": "or"
  }
}
